ovos_PHAL_plugin_mk2_v6_fan_control/__init__.py
ovos_PHAL_plugin_mk2_v6_fan_control/version.py
ovos_PHAL_plugin_mk2_fan_control-0.0.1.dist-info/LICENSE
ovos_PHAL_plugin_mk2_fan_control-0.0.1.dist-info/METADATA
ovos_PHAL_plugin_mk2_fan_control-0.0.1.dist-info/WHEEL
ovos_PHAL_plugin_mk2_fan_control-0.0.1.dist-info/entry_points.txt
ovos_PHAL_plugin_mk2_fan_control-0.0.1.dist-info/top_level.txt
ovos_PHAL_plugin_mk2_fan_control-0.0.1.dist-info/zip-safe
ovos_PHAL_plugin_mk2_fan_control-0.0.1.dist-info/RECORD
